python_bap/__init__.py
python_bap/main.py
python_bap-1.0.1.dist-info/METADATA
python_bap-1.0.1.dist-info/WHEEL
python_bap-1.0.1.dist-info/entry_points.txt
python_bap-1.0.1.dist-info/RECORD
