Metadata-Version: 2.4
Name: python-bap
Version: 1.0.1
Summary: 
Author: Dave Martinez
Author-email: 34991082+dkm-coder@users.noreply.github.com
Requires-Python: >=3.9
Classifier: Programming Language :: Python :: 3
Classifier: Programming Language :: Python :: 3.9
Classifier: Programming Language :: Python :: 3.10
Classifier: Programming Language :: Python :: 3.11
Classifier: Programming Language :: Python :: 3.12
Classifier: Programming Language :: Python :: 3.13
Classifier: Programming Language :: Python :: 3.14
Requires-Dist: requests (>=2.32.5,<3.0.0)
Requires-Dist: typer (>=0.21.0,<0.22.0)
Requires-Dist: urllib3 (<2)
